stx_logger_util/__init__.py
stx_logger_util/decorators.py
stx_logger_util/function_types.py
stx_logger_util/log_admin.py
stx_logger_util/log_message.py
tests/__init__.py
tests/test_decorators.py
stx_logger_util-0.0.5.dist-info/LICENSE
stx_logger_util-0.0.5.dist-info/METADATA
stx_logger_util-0.0.5.dist-info/WHEEL
stx_logger_util-0.0.5.dist-info/top_level.txt
stx_logger_util-0.0.5.dist-info/RECORD
